linkdapi/LinkdAPI.py
linkdapi/__init__.py
linkdapi/asyncLinkdAPI.py
linkdapi-1.0.7.dist-info/licenses/LICENSE
linkdapi-1.0.7.dist-info/METADATA
linkdapi-1.0.7.dist-info/WHEEL
linkdapi-1.0.7.dist-info/top_level.txt
linkdapi-1.0.7.dist-info/RECORD
