Metadata-Version: 2.4
Name: linkdapi
Version: 1.0.7
Summary: Python SDK for LinkdAPI - The best API for professional Data
Author-email: LinkdAPI <support@linkdapi.com>
License-Expression: MIT
Project-URL: Homepage, https://linkdapi.com
Project-URL: Documentation, https://linkdapi.com/docs
Project-URL: Repository, https://github.com/linkdAPI/linkdapi-SDK
Keywords: recruitment-tools,lead-generation,business-intelligence,data-extraction,reverse-lookup,contact-info,people-search,social-media-api,b2b-data,sales-intelligence
Classifier: Programming Language :: Python :: 3
Classifier: Intended Audience :: Developers
Classifier: Intended Audience :: Science/Research
Classifier: Intended Audience :: Financial and Insurance Industry
Classifier: Topic :: Internet :: WWW/HTTP
Classifier: Topic :: Office/Business
Classifier: Topic :: Software Development :: Libraries
Requires-Python: >=3.10
License-File: LICENSE
Requires-Dist: httpx>=0.28.1
Dynamic: license-file
